practiso_mcp/__init__.py
practiso_mcp/__main__.py
state_tracking/__init__.py
practiso_mcp-0.1.3.dist-info/WHEEL
practiso_mcp-0.1.3.dist-info/entry_points.txt
practiso_mcp-0.1.3.dist-info/METADATA
practiso_mcp-0.1.3.dist-info/RECORD
